flexytg/__init__.py
flexytg/Apis/GetApis.py
flexytg/Apis/__init__.py
flexytg/sessions/__init__.py
flexytg/sessions/analyze_session.py
flexytg/sessions/create_session.py
flexytg/sessions/json_gogram.py
flexytg/sessions/sql_hydrogram.py
flexytg/sessions/sql_pyrogram.py
flexytg/sessions/sql_telethon.py
flexytg/sessions/string_gogram.py
flexytg/sessions/string_hydrogram.py
flexytg/sessions/string_pyrogram.py
flexytg/sessions/string_telethon.py
flexytg-1.0.0.dist-info/METADATA
flexytg-1.0.0.dist-info/WHEEL
flexytg-1.0.0.dist-info/top_level.txt
flexytg-1.0.0.dist-info/RECORD
