Metadata-Version: 2.1
Name: flexytg
Version: 1.0.0
Summary: Module To Making Using Mt Proto Flexable
Home-page: https://github.com/Aayco/Flexytg
Author: Amiru Mohammed
License: MIT
Classifier: Programming Language :: Python :: 3
Requires-Python: >=3
